PyCurve/__init__.py
PyCurve/actuarial_implementation.py
PyCurve/bjork_christensen.py
PyCurve/bjork_christensen_augmented.py
PyCurve/cubic.py
PyCurve/curve.py
PyCurve/hull_white.py
PyCurve/linear.py
PyCurve/nelson_siegel.py
PyCurve/simulation.py
PyCurve/svensson_nelson_siegel.py
PyCurve/vasicek.py
PyCurve-0.1.4.dist-info/LICENSE
PyCurve-0.1.4.dist-info/METADATA
PyCurve-0.1.4.dist-info/WHEEL
PyCurve-0.1.4.dist-info/top_level.txt
PyCurve-0.1.4.dist-info/RECORD
