Metadata-Version: 2.1
Name: PyCurve
Version: 0.1.4
Summary: Interest Rate Yield Curve Toolkit
Home-page: https://github.com/ahgperrin/PyCurve
Author: Antoine Perrin
Author-email: antoineperrin.pro1@gmail.com
License: UNKNOWN
Platform: UNKNOWN
Classifier: Programming Language :: Python :: 3.9
Classifier: License :: OSI Approved :: MIT License
Classifier: Operating System :: OS Independent
Requires-Dist: matplotlib
Requires-Dist: pandas
Requires-Dist: numpy
Requires-Dist: scipy
Requires-Dist: typing
